hidp_wagtail/README.md
hidp_wagtail/__init__.py
hidp_wagtail/apps.py
hidp_wagtail/checks.py
hidp_wagtail/context_processors.py
hidp_wagtail/middleware.py
hidp_wagtail/wagtail_hooks.py
hidp_wagtail/static/css/wagtail_hidp.css
hidp_wagtail/static/css/wagtail_hidp_post_login.css
hidp_wagtail/static/css/wagtail_hidp_pre_login.css
hidp_wagtail/templates/hidp/base.html
hidp_wagtail/templates/hidp/base_post_login.html
hidp_wagtail/templates/hidp/base_pre_login.html
hidp_wagtail/templates/hidp/messages.html
hidp_wagtail/templates/hidp/includes/federated/oidc_provider_list.html
hidp_wagtail/templates/hidp/includes/federated/oidc_provider_list_option.html
hidp_wagtail/templates/icons/facebook.html
hidp_wagtail/templates/icons/google.html
hidp_wagtail/templates/icons/linkedin.html
hidp_wagtail/templates/icons/microsoft.html
django_hidp_wagtail-1.2.0.dist-info/METADATA
django_hidp_wagtail-1.2.0.dist-info/WHEEL
django_hidp_wagtail-1.2.0.dist-info/top_level.txt
django_hidp_wagtail-1.2.0.dist-info/RECORD
