Metadata-Version: 2.4
Name: django-hidp-wagtail
Version: 1.2.0
Summary: A Wagtail-themed template pack for HIdP
Author-email: Ramon de Jezus <rdejezus@leukeleu.nl>, Wouter de Vries <wdevries@leukeleu.nl>
License-Expression: BSD-3-Clause
Project-URL: Repository, https://github.com/leukeleu/django-hidp-wagtail/
Project-URL: Issues, https://github.com/leukeleu/django-hidp-wagtail/issues
Project-URL: Releasenotes, https://github.com/leukeleu/django-hidp-wagtail/releases
Classifier: Development Status :: 5 - Production/Stable
Classifier: Framework :: Django
Classifier: Framework :: Wagtail
Classifier: Intended Audience :: Developers
Classifier: Programming Language :: Python :: 3
Requires-Python: >=3.11
Requires-Dist: django-hidp<2,>=1.5.0
